MANIFEST.in
README.md
requirements-dev.txt
requirements.txt
setup.cfg
setup.py
version.py
falcon_swagger.egg-info/PKG-INFO
falcon_swagger.egg-info/SOURCES.txt
falcon_swagger.egg-info/dependency_links.txt
falcon_swagger.egg-info/requires.txt
falcon_swagger.egg-info/top_level.txt
falconswagger/__init__.py
falconswagger/constants.py
falconswagger/exceptions.py
falconswagger/hooks.py
falconswagger/json_builder.py
falconswagger/middlewares.py
falconswagger/mixins.py
falconswagger/router.py
falconswagger/swagger_api.py
falconswagger/swagger_schema_extended.json
falconswagger/swagger_template.json
falconswagger/utils.py
falconswagger/models/__init__.py
falconswagger/models/http.py
falconswagger/models/logger.py
falconswagger/models/orm/__init__.py
falconswagger/models/orm/http.py
falconswagger/models/orm/redis.py
falconswagger/models/orm/redis_base.py
falconswagger/models/orm/session.py
falconswagger/models/orm/sqlalchemy_redis.py
tests/__init__.py
tests/conftest.py
tests/integration/__init__.py
tests/integration/conftest.py