Metadata-Version: 1.1
Name: falcon-swagger
Version: 0.12.3
Summary: A Falcon Framework extension featuring Swagger, SQLAlchemy and Redis
Home-page: https://github.com/dutradda/falcon-swagger
Author: Diogo Dutra
Author-email: dutradda@gmail.com
License: MIT
Download-URL: http://github.com/dutradda/falcon-swagger/archive/master.zip
Keywords: falcon framework swagger openapi sqlalchemy redis crud
Platform: UNKNOWN
Classifier: License :: OSI Approved :: MIT License
Classifier: Development Status :: 3 - Alpha
Classifier: Intended Audience :: Developers
Classifier: Natural Language :: English
Classifier: Programming Language :: Python :: 3.5
Classifier: Topic :: Internet :: WWW/HTTP :: WSGI :: Middleware
Classifier: Topic :: Database :: Front-Ends
Classifier: Topic :: Software Development :: Libraries :: Python Modules
